<annotation>
	<folder>my-project-name</folder>
	<filename>000013.jpg</filename>
	<path>/my-project-name/000013.jpg</path>
	<source>
		<database>Unspecified</database>
	</source>
	<size>
		<width>4160</width>
		<height>3120</height>
		<depth>3</depth>
	</size>
	<object>
		<name>daun</name>
		<pose>Unspecified</pose>
		<truncated>Unspecified</truncated>
		<difficult>Unspecified</difficult>
		<bndbox>
			<xmin>1577</xmin>
			<ymin>883</ymin>
			<xmax>2403</xmax>
			<ymax>1728</ymax>
		</bndbox>
	</object>
	<object>
		<name>daun</name>
		<pose>Unspecified</pose>
		<truncated>Unspecified</truncated>
		<difficult>Unspecified</difficult>
		<bndbox>
			<xmin>2248</xmin>
			<ymin>2126</ymin>
			<xmax>3149</xmax>
			<ymax>2840</ymax>
		</bndbox>
	</object>
	<object>
		<name>daun</name>
		<pose>Unspecified</pose>
		<truncated>Unspecified</truncated>
		<difficult>Unspecified</difficult>
		<bndbox>
			<xmin>1260</xmin>
			<ymin>1976</ymin>
			<xmax>2005</xmax>
			<ymax>2865</ymax>
		</bndbox>
	</object>
	<object>
		<name>daun</name>
		<pose>Unspecified</pose>
		<truncated>Unspecified</truncated>
		<difficult>Unspecified</difficult>
		<bndbox>
			<xmin>2534</xmin>
			<ymin>1448</ymin>
			<xmax>3081</xmax>
			<ymax>1852</ymax>
		</bndbox>
	</object>
	<object>
		<name>daun</name>
		<pose>Unspecified</pose>
		<truncated>Unspecified</truncated>
		<difficult>Unspecified</difficult>
		<bndbox>
			<xmin>2266</xmin>
			<ymin>1778</ymin>
			<xmax>2832</xmax>
			<ymax>2076</ymax>
		</bndbox>
	</object>
	<object>
		<name>daun</name>
		<pose>Unspecified</pose>
		<truncated>Unspecified</truncated>
		<difficult>Unspecified</difficult>
		<bndbox>
			<xmin>1757</xmin>
			<ymin>1846</ymin>
			<xmax>2254</xmax>
			<ymax>2250</ymax>
		</bndbox>
	</object>
	<object>
		<name>daun</name>
		<pose>Unspecified</pose>
		<truncated>Unspecified</truncated>
		<difficult>Unspecified</difficult>
		<bndbox>
			<xmin>1595</xmin>
			<ymin>1622</ymin>
			<xmax>1956</xmax>
			<ymax>1958</ymax>
		</bndbox>
	</object>
	<object>
		<name>daun</name>
		<pose>Unspecified</pose>
		<truncated>Unspecified</truncated>
		<difficult>Unspecified</difficult>
		<bndbox>
			<xmin>2148</xmin>
			<ymin>1622</ymin>
			<xmax>2465</xmax>
			<ymax>1771</ymax>
		</bndbox>
	</object>
</annotation>