<annotation>
	<folder>my-project-name</folder>
	<filename>000030.jpg</filename>
	<path>/my-project-name/000030.jpg</path>
	<source>
		<database>Unspecified</database>
	</source>
	<size>
		<width>4160</width>
		<height>3120</height>
		<depth>3</depth>
	</size>
	<object>
		<name>daun</name>
		<pose>Unspecified</pose>
		<truncated>Unspecified</truncated>
		<difficult>Unspecified</difficult>
		<bndbox>
			<xmin>1359</xmin>
			<ymin>1579</ymin>
			<xmax>2192</xmax>
			<ymax>2573</ymax>
		</bndbox>
	</object>
	<object>
		<name>daun</name>
		<pose>Unspecified</pose>
		<truncated>Unspecified</truncated>
		<difficult>Unspecified</difficult>
		<bndbox>
			<xmin>2229</xmin>
			<ymin>441</ymin>
			<xmax>3217</xmax>
			<ymax>1274</ymax>
		</bndbox>
	</object>
	<object>
		<name>daun</name>
		<pose>Unspecified</pose>
		<truncated>Unspecified</truncated>
		<difficult>Unspecified</difficult>
		<bndbox>
			<xmin>1620</xmin>
			<ymin>37</ymin>
			<xmax>2024</xmax>
			<ymax>535</ymax>
		</bndbox>
	</object>
	<object>
		<name>daun</name>
		<pose>Unspecified</pose>
		<truncated>Unspecified</truncated>
		<difficult>Unspecified</difficult>
		<bndbox>
			<xmin>2235</xmin>
			<ymin>75</ymin>
			<xmax>2496</xmax>
			<ymax>485</ymax>
		</bndbox>
	</object>
	<object>
		<name>daun</name>
		<pose>Unspecified</pose>
		<truncated>Unspecified</truncated>
		<difficult>Unspecified</difficult>
		<bndbox>
			<xmin>1533</xmin>
			<ymin>622</ymin>
			<xmax>2043</xmax>
			<ymax>1262</ymax>
		</bndbox>
	</object>
	<object>
		<name>daun</name>
		<pose>Unspecified</pose>
		<truncated>Unspecified</truncated>
		<difficult>Unspecified</difficult>
		<bndbox>
			<xmin>626</xmin>
			<ymin>752</ymin>
			<xmax>1508</xmax>
			<ymax>1548</ymax>
		</bndbox>
	</object>
	<object>
		<name>daun</name>
		<pose>Unspecified</pose>
		<truncated>Unspecified</truncated>
		<difficult>Unspecified</difficult>
		<bndbox>
			<xmin>1993</xmin>
			<ymin>1367</ymin>
			<xmax>2322</xmax>
			<ymax>1579</ymax>
		</bndbox>
	</object>
	<object>
		<name>daun</name>
		<pose>Unspecified</pose>
		<truncated>Unspecified</truncated>
		<difficult>Unspecified</difficult>
		<bndbox>
			<xmin>2192</xmin>
			<ymin>1759</ymin>
			<xmax>2459</xmax>
			<ymax>2206</ymax>
		</bndbox>
	</object>
	<object>
		<name>daun</name>
		<pose>Unspecified</pose>
		<truncated>Unspecified</truncated>
		<difficult>Unspecified</difficult>
		<bndbox>
			<xmin>1564</xmin>
			<ymin>1324</ymin>
			<xmax>1676</xmax>
			<ymax>1541</ymax>
		</bndbox>
	</object>
	<object>
		<name>daun</name>
		<pose>Unspecified</pose>
		<truncated>Unspecified</truncated>
		<difficult>Unspecified</difficult>
		<bndbox>
			<xmin>2155</xmin>
			<ymin>1218</ymin>
			<xmax>2459</xmax>
			<ymax>1485</ymax>
		</bndbox>
	</object>
	<object>
		<name>daun</name>
		<pose>Unspecified</pose>
		<truncated>Unspecified</truncated>
		<difficult>Unspecified</difficult>
		<bndbox>
			<xmin>2092</xmin>
			<ymin>733</ymin>
			<xmax>2279</xmax>
			<ymax>1144</ymax>
		</bndbox>
	</object>
	<object>
		<name>daun</name>
		<pose>Unspecified</pose>
		<truncated>Unspecified</truncated>
		<difficult>Unspecified</difficult>
		<bndbox>
			<xmin>1688</xmin>
			<ymin>1448</ymin>
			<xmax>1918</xmax>
			<ymax>1566</ymax>
		</bndbox>
	</object>
	<object>
		<name>daun</name>
		<pose>Unspecified</pose>
		<truncated>Unspecified</truncated>
		<difficult>Unspecified</difficult>
		<bndbox>
			<xmin>1732</xmin>
			<ymin>1280</ymin>
			<xmax>1925</xmax>
			<ymax>1386</ymax>
		</bndbox>
	</object>
</annotation>